mslang/__init__.py
mslang/mslang.py
mslang-1.1.dist-info/METADATA
mslang-1.1.dist-info/WHEEL
mslang-1.1.dist-info/top_level.txt
mslang-1.1.dist-info/RECORD
